skorch/__init__.py
skorch/_doctor.py
skorch/_version.py
skorch/classifier.py
skorch/cli.py
skorch/dataset.py
skorch/exceptions.py
skorch/helper.py
skorch/hf.py
skorch/history.py
skorch/net.py
skorch/probabilistic.py
skorch/regressor.py
skorch/scoring.py
skorch/setter.py
skorch/toy.py
skorch/utils.py
skorch/callbacks/__init__.py
skorch/callbacks/base.py
skorch/callbacks/logging.py
skorch/callbacks/lr_scheduler.py
skorch/callbacks/regularization.py
skorch/callbacks/scoring.py
skorch/callbacks/training.py
skorch/llm/__init__.py
skorch/llm/classifier.py
skorch/llm/prompts.py
skorch/tests/__init__.py
skorch/tests/conftest.py
skorch/tests/flycheck_test_utils.py
skorch/tests/test_classifier.py
skorch/tests/test_cli.py
skorch/tests/test_dataset.py
skorch/tests/test_doctor.py
skorch/tests/test_helper.py
skorch/tests/test_hf.py
skorch/tests/test_history.py
skorch/tests/test_net.py
skorch/tests/test_probabilistic.py
skorch/tests/test_regressor.py
skorch/tests/test_scoring.py
skorch/tests/test_setter.py
skorch/tests/test_toy.py
skorch/tests/test_utils.py
skorch/tests/callbacks/test_all.py
skorch/tests/callbacks/test_logging.py
skorch/tests/callbacks/test_lr_scheduler.py
skorch/tests/callbacks/test_regularization.py
skorch/tests/callbacks/test_scoring.py
skorch/tests/callbacks/test_training.py
skorch/tests/llm/test_llm_classifier.py
skorch-1.3.1.dist-info/licenses/LICENSE
skorch-1.3.1.dist-info/METADATA
skorch-1.3.1.dist-info/WHEEL
skorch-1.3.1.dist-info/top_level.txt
skorch-1.3.1.dist-info/RECORD
