Metadata-Version: 2.4
Name: skorch
Version: 1.3.1
Summary: scikit-learn compatible neural network library for pytorch
Author: Marian Tietz, Thomas J. Fan, Daniel Nouri, Benjamin Bossan, skorch Developers
License-Expression: BSD-3-Clause
Classifier: Programming Language :: Python :: 3.10
Classifier: Programming Language :: Python :: 3.11
Classifier: Programming Language :: Python :: 3.12
Classifier: Programming Language :: Python :: 3.13
Classifier: Programming Language :: Python :: 3 :: Only
Classifier: Topic :: Scientific/Engineering
Classifier: Topic :: Scientific/Engineering :: Artificial Intelligence
Classifier: Topic :: Software Development
Classifier: Topic :: Software Development :: Libraries
Classifier: Topic :: Software Development :: Libraries :: Python Modules
Requires-Python: >=3.10
License-File: LICENSE
Requires-Dist: numpy>=1.13.3
Requires-Dist: scikit-learn>=0.22.0
Requires-Dist: scipy>=1.1.0
Requires-Dist: tabulate>=0.7.7
Requires-Dist: tqdm>=4.14.0
Provides-Extra: dev
Requires-Dist: pylint; extra == "dev"
Requires-Dist: flake8; extra == "dev"
Requires-Dist: future>=0.17.1; extra == "dev"
Provides-Extra: test
Requires-Dist: pytest>=3.4; extra == "test"
Requires-Dist: pytest-cov; extra == "test"
Requires-Dist: flaky; extra == "test"
Provides-Extra: docs
Requires-Dist: sphinx; extra == "docs"
Requires-Dist: sphinx_rtd_theme; extra == "docs"
Requires-Dist: numpydoc; extra == "docs"
Provides-Extra: extended
Requires-Dist: accelerate>=0.22.0; extra == "extended"
Requires-Dist: tensorboard>=1.14.0; extra == "extended"
Requires-Dist: wandb>=0.12.17; extra == "extended"
Requires-Dist: neptune; extra == "extended"
Requires-Dist: sacred; extra == "extended"
Requires-Dist: jupyter; extra == "extended"
Requires-Dist: matplotlib>=2.0.2; extra == "extended"
Requires-Dist: pandas; extra == "extended"
Requires-Dist: openpyxl; extra == "extended"
Requires-Dist: transformers; extra == "extended"
Requires-Dist: tokenizers; extra == "extended"
Requires-Dist: safetensors>=0.3.1; extra == "extended"
Requires-Dist: protobuf; extra == "extended"
Requires-Dist: gpytorch>=1.5; extra == "extended"
Requires-Dist: pillow; extra == "extended"
Requires-Dist: fire; extra == "extended"
Dynamic: license-file
